explainax/__init__.py
explainax/_modidx.py
explainax/imports.py
explainax/linear_model.py
explainax/attr/__init__.py
explainax/attr/base.py
explainax/attr/lime.py
explainax-0.0.1.dist-info/LICENSE
explainax-0.0.1.dist-info/METADATA
explainax-0.0.1.dist-info/WHEEL
explainax-0.0.1.dist-info/entry_points.txt
explainax-0.0.1.dist-info/top_level.txt
explainax-0.0.1.dist-info/RECORD
